{
  "Records": [
    {
      "EventVersion": "1.0",
      "EventSubscriptionArn": "arn:aws:sns:us-east-1:123456789012:netbox-notices-ses-tracking:abcd1234",
      "EventSource": "aws:sns",
      "Sns": {
        "Type": "Notification",
        "MessageId": "msg-open-001",
        "TopicArn": "arn:aws:sns:us-east-1:123456789012:netbox-notices-ses-tracking",
        "Subject": "Amazon SES Email Event Notification",
        "Message": "{\"eventType\":\"Open\",\"mail\":{\"timestamp\":\"2026-01-15T12:06:00.000Z\",\"messageId\":\"ses-msg-id-001\",\"source\":\"noc@example.com\",\"destination\":[\"customer@example.com\"],\"tags\":{\"notification_id\":[\"42\"]}},\"open\":{\"timestamp\":\"2026-01-15T12:30:00.000Z\",\"ipAddress\":\"198.51.100.10\",\"userAgent\":\"Mozilla/5.0 (Windows NT 10.0; Win64; x64) AppleWebKit/537.36\"}}",
        "Timestamp": "2026-01-15T12:30:01.000Z"
      }
    }
  ]
}
